<?xml version='1.0' encoding='utf-8'?>
<SolveMurder3>


    <General>
        <Text>~b~Detective~s~ en caso de asesinato requerido</Text>
        <Text>Agente muerto tras una parada de tráfico</Text>
    </General>


    <Approach>
        <Text>Habla con los ~HC_43~Detective~s~ para que te informen sobre la escena.</Text>
    </Approach>


    <Characters>
        <Text>~HC_43~Detective~s~:</Text>
        <Text>~y~You~s~:</Text>
        <Text>~p~Laborant~s~:</Text>
        <Text>~g~Witness~s~:</Text>
        <Text>~r~Suspect~s~:</Text>
    </Characters>


    <TalkToDetective>
        <Dialogue>¡Hola ~HC_43~Detective~s~! ¡Qué gran escena tenemos aquí! ¿Qué está pasando?</Dialogue>
        <Dialogue>¡Hola, sí definitivamente! Lamentablemente tenemos uno de nuestros ~b~oficiales ~r~murdered~s~ en una parada de tráfico...</Dialogue>
        <Dialogue>Ahora mismo no tenemos ni idea de quién ha sido, por eso te hemos llamado a ti, alguien que tiene bastante experiencia.</Dialogue>
        <Dialogue>He oído hablar del caso de ~g~Mount Chiliad~s~ en la gasolinera, ¡lo resolviste bien!</Dialogue>
        <Dialogue>Gracias, señor, veamos qué puedo encontrar sobre este caso.</Dialogue>
        <Dialogue>Oh lo siento, si claro, por favor busca ~y~evidencias~s~ en la escena, cualquier cosa puede ayudar.</Dialogue>
        <Dialogue>Puedes pulsar ~y~{0}~s~ para ~y~recoger~s~ la ~y~evidencia~s~ cuando estés junto a ella. ~g~¡Buena suerte~s~!</Dialogue>
        <Dialogue>Ve a la zona cerrada y busca pruebas, pulsa ~y~{1}~s~ para recoger ~y~evidencias~s~.</Dialogue>
        <Dialogue>Revisa la escena de nuevo, ¡todavía te faltan algunos!</Dialogue>
    </TalkToDetective>


    <SearchForEvidence>
        <Dialogue>Aquí hay un poco de ~HC_211~help~s~.</Dialogue>
        <Dialogue>~r~No hay pruebas~s~ cerca.</Dialogue>

        <Dialogue>Un ~o~rifle~s~, esto sólo puede ser los sospechosos o los oficiales.</Dialogue>
        <Dialogue>Esta tiene que ser la ~o~cartera~s~ del sospechoso...</Dialogue>
        <Dialogue>Un ~o~teléfono móvil~s~, si sólo tuviera la contraseña.</Dialogue>
        <Dialogue>¿Una cerveza? Alguien la ha tirado por la ventana.</Dialogue>

        <Dialogue>Un cuchillo... tiene sangre.</Dialogue>
        <Dialogue>Una tarjeta de identificación, mejor se la doy al Laborante.</Dialogue>
        <Dialogue>Un ~o~USB-stick~s~, me pregunto qué tendrá.</Dialogue>
        <Dialogue>Una ~o~bolsa~s~... No debería poner más huellas en él.</Dialogue>

        <Dialogue>Una ~o~pistola~s~... no parece de policía.</Dialogue>
        <Dialogue>Una matrícula... ¿podría ser la del sospechoso?</Dialogue>
        <Dialogue>Un ~o~shoe~s~, no emitido por ningún departamento de policía.</Dialogue>
        <Dialogue>Un ~o~whisky~s~... Me gustaría poder tomar una foto :p</Dialogue>

        <Dialogue>Habla con el detective sobre las pruebas encontradas.</Dialogue>
    </SearchForEvidence>


    <AgainTalkToDetective>
        <Dialogue>Hey, he encontrado algunas pruebas interesantes, que nos ayudará.</Dialogue>
        <Dialogue>Muy bien, ¡dímelo!</Dialogue>
        <Dialogue>Encontré {0}.</Dialogue>
        <Dialogue>un rifle, una cartera, un teléfono y una cerveza</Dialogue>
        <Dialogue>un cuchillo, una identificación, una memoria USB y una bolsa</Dialogue>
        <Dialogue>una pistola, una matrícula, un zapato y una botella de whisky</Dialogue>
        <Dialogue>Estoy bastante seguro de que esta es el arma homicida.</Dialogue>
        <Dialogue>También deberíamos poder encontrar información sobre el sospechoso.</Dialogue>
        <Dialogue>¡Claro! ¡Ve al ~p~Laborant~s~, él analizará las pruebas y averiguará más!</Dialogue>
        <Dialogue>Usa ~y~{1}~s~ para hablar con el ~p~Laborante~s~ sobre las ~y~evidencias~s~.</Dialogue>
    </AgainTalkToDetective>


    <TalkToLaborant>
        <Dialogue>Hola señor, gracias por venir. He encontrado muchas pruebas, ¿le importaría comprobarlo?</Dialogue>
        <Dialogue>Hola a ti también. Sí, claro, ese es mi trabajo. Por favor, entrégueme las pruebas.</Dialogue>
        <Dialogue>Gracias, voy a comprobarlo rápidamente.</Dialogue>
        <Dialogue>Pulse ~y~{3}~s~ de nuevo para hablar</Dialogue>
        <Dialogue>Muy bien, he comprobado las pruebas.</Dialogue>

        <Dialogue>¡El propietario del ~o~{3}~s~ es ~o~{4}~s~!</Dialogue> 
        <Dialogue>En el ~o~{3}~s~ encontré una licencia de conducir de ~o~{4}~s~.</Dialogue>
        <Dialogue>¡En el ~o~{3}~s~ encontré el nombre del propietario: ~o~{4}~s~!</Dialogue>
        <Dialogue>El ~o~{3}~s~ apenas se leía, pero el nombre es ~o~{4}~s~.</Dialogue>
        <Dialogue>En el ~o~{3}~s~ encontré archivos de ~o~{4}~s~.</Dialogue>
        <Dialogue>El número de serie de ~o~{3}~s~ vuelve a ~o~{4}~s~.</Dialogue>
        <Dialogue>El ~o~{3}~s~ vuelve a ~o~{4}~s~.</Dialogue>

        <Dialogue>¡Este es probablemente nuestro sospechoso!</Dialogue>
        <Dialogue>¡Este podría ser nuestro sospechoso!</Dialogue>

        <Dialogue>El detective quería hablar contigo otra vez, ve con él otra vez, por favor.</Dialogue>
        <Dialogue>Vuelve a hablar con los ~HC_43~Detective~s~.</Dialogue>
    </TalkToLaborant>


    <TalkToDetectiveAnalyzedEvidence>
        <Dialogue>¿Tenemos alguna información nueva?</Dialogue>
        <Dialogue>¡Sí! ¡El ~o~{4}~s~ nos lleva en la dirección correcta!</Dialogue>
        <Dialogue>¡Perfecto! Además tenemos una ~g~testigo~s~ allí, esperemos que nos pueda dar más detalles.</Dialogue>
        <Dialogue>Ve a la ~g~testigo~s~ y habla con ella usando ~y~{0}~s~</Dialogue>
    </TalkToDetectiveAnalyzedEvidence>


    <TalkToWitness>

        <Vehicle>
            <Dialogue>Hola señora, soy el ~y~Detective~s~ en este caso, ¿ha sido testigo de algo?</Dialogue>
            <Dialogue>Hola ~y~Detective~s~, mi Nombre es {5} y si, tengo algunas infos.</Dialogue>
            <Dialogue>Al principio quería ir a comprar a los supermercados.</Dialogue>
            <Dialogue>Por supuesto, me di cuenta de esta parada de tráfico con las luces azules parpadeantes, cuando de repente vi un vehículo que se alejaba de forma enérgica.</Dialogue>
            <Dialogue>No pude ver al conductor ni la matrícula, pero el modelo era un ~o~{0}~s~.</Dialogue>
            <Dialogue>Impresionante, gracias por la información, vamos a ver lo que el despacho puede averiguar.</Dialogue>
        </Vehicle>

        <House>
            <Dialogue>Hola señora, soy el ~y~Detective~s~ en este caso, ¿ha sido testigo de algo?</Dialogue>
            <Dialogue>Hola ~y~Detective~s~, mi Nombre es {5} y si, tengo algunas infos.</Dialogue>
            <Dialogue>Al principio quería ir a comprar a los supermercados, soy de aquí.</Dialogue>
            <Dialogue>Por supuesto, me di cuenta de esta parada de tráfico con las luces azules intermitentes, cuando de repente vi a una persona huyendo.</Dialogue>
            <Dialogue>Creo que reconocí a la persona, el sospechoso tiene que ser ~o~{4}~s~.</Dialogue>
            <Dialogue>Impresionante, gracias por la información, vamos a ver lo que el despacho puede averiguar.</Dialogue>
        </House>
        
    </TalkToWitness>


    <SearchForSuspect>

        <Vehicle>
            <Dialogue>Despacho, ¿puede comprobar las cámaras de tráfico para un vehículo sospechoso de asesinato, el modelo es ~o~{0}~s~.</Dialogue>
            <Dialogue>Comprobando...</Dialogue>
            <Dialogue>Tiene un golpe en un vehículo, está marcado en su GPS</Dialogue>
            
            <Dialogue>Nuevo ~r~ALPR Hit ~s~on ~y~Vehicle {1}!~s~</Dialogue>
        </Vehicle>

        <House>
            <Dialogue>Despacho, ¿puede establecer la ruta a la casa de los sospechosos?</Dialogue>
            <Dialogue>Comprobando...</Dialogue>
            <Dialogue>Tienes la casa, está marcada en tu GPS</Dialogue>
        </House>

    </SearchForSuspect>


    <InPursuit>
        <Dialogue>¡Mierda, la policía!</Dialogue>
    </InPursuit>


    <QuestioningSuspect>
        <Dialogue>Cuando estés listo, ~r~confronta al sospechoso~s~ sobre sus acciones, usa ~y~{0}~s~ para hablar.</Dialogue>
        <Dialogue>¡En nombre de la ley, está bajo arresto por el asesinato de un oficial de policía!</Dialogue>
        <Dialogue>Voy a leerte tus derechos Miranda...  * reads miranda rights *</Dialogue>
        <Dialogue>¿Por qué has huido?</Dialogue>
        <Dialogue>Señor, siento mucho lo que he hecho, la he cagado.</Dialogue>
        <Dialogue>Corrí porque tenía miedo, eso es todo.</Dialogue>
        <Dialogue>¡Has asesinado a un agente de policía!</Dialogue>
        <Dialogue>¿Qué? ¿Está muerto? Yo sólo... No quería ir a la cárcel, pero no quería matarlo...</Dialogue>
        <Dialogue>Le disparaste...</Dialogue>
        <Dialogue>Sólo quería asustarlo, para poder escapar y ser libre.</Dialogue>
        <Dialogue>Te meterán en la cárcel y probablemente no salgas muy pronto...</Dialogue>
        <Dialogue>Lleven a los sospechosos a la cárcel.</Dialogue>
    </QuestioningSuspect>


    <End>
        <Text>Pulse ~y~End~s~ en cualquier momento para finalizar la llamada.</Text>
        <Text>Somos ~g~Código 4.~s~</Text>
    </End>


</SolveMurder3>